pySEACR/__main__.py
pySEACR/auc_from_bdg.py
pySEACR/normalize.py
pySEACR/normalize_R.py
pySEACR/pct_remain.py
pySEACR/threshold_finder.py
pySEACR/utils.py
pySEACR-0.3.dist-info/LICENSE
pySEACR-0.3.dist-info/METADATA
pySEACR-0.3.dist-info/WHEEL
pySEACR-0.3.dist-info/top_level.txt
pySEACR-0.3.dist-info/RECORD
